baseballcv/README.md
baseballcv/__init__.py
baseballcv/assets/baseballcvlogo.png
baseballcv/assets/pbr_baseballcv.jpg
baseballcv/datasets/README.md
baseballcv/datasets/__init__.py
baseballcv/datasets/formats/datasets_coco_detection.py
baseballcv/datasets/formats/datasets_jsonl_detection.py
baseballcv/datasets/processing/datasets_processor.py
baseballcv/datasets/translation/dataset_translator.py
baseballcv/datasets/translation/formats.py
baseballcv/functions/README.md
baseballcv/functions/__init__.py
baseballcv/functions/baseball_tools.py
baseballcv/functions/dataset_tools.py
baseballcv/functions/load_tools.py
baseballcv/functions/savant_scraper.py
baseballcv/functions/utils/__init__.py
baseballcv/functions/utils/baseball_utils/README.md
baseballcv/functions/utils/baseball_utils/__init__.py
baseballcv/functions/utils/baseball_utils/command_analyzer.py
baseballcv/functions/utils/baseball_utils/distance_to_zone.py
baseballcv/functions/utils/baseball_utils/glove_tracker.py
baseballcv/functions/utils/savant_utils/__init__.py
baseballcv/functions/utils/savant_utils/crawler.py
baseballcv/functions/utils/savant_utils/gameday.py
baseballcv/functions/utils/utils.py
baseballcv/model/README.md
baseballcv/model/__init__.py
baseballcv/model/od/__init__.py
baseballcv/model/od/detr/detr.py
baseballcv/model/od/detr/rfdetr.py
baseballcv/model/od/yolo/LICENSE
baseballcv/model/od/yolo/yolo.py
baseballcv/model/utils/__init__.py
baseballcv/model/utils/model_function_utils.py
baseballcv/model/utils/model_visualization_tools.py
baseballcv/model/vlm/__init__.py
baseballcv/model/vlm/florence2/florence2.py
baseballcv/model/vlm/paligemma2/paligemma2.py
baseballcv/utilities/__init__.py
baseballcv/utilities/dependencies/git_dependency_installer.py
baseballcv/utilities/logger/baseballcv_logger.py
baseballcv/utilities/logger/baseballcv_prog_bar.py
baseballcv-0.1.24.dist-info/LICENSE
baseballcv-0.1.24.dist-info/LICENSE-MLB-AGPL.txt
baseballcv-0.1.24.dist-info/METADATA
baseballcv-0.1.24.dist-info/WHEEL
baseballcv-0.1.24.dist-info/RECORD
