Metadata-Version: 2.3
Name: baseballcv
Version: 0.1.24
Summary: A collection of tools and models designed to aid in the use of Computer Vision in baseball.
Author: Dylan Drummey
Author-email: dylandrummey22@gmail.com
Requires-Python: >=3.9, !=3.9.7, <4.0
Classifier: Operating System :: OS Independent
Classifier: Programming Language :: Python :: 3
Requires-Dist: autodistill (==0.1.29)
Requires-Dist: autodistill-grounded-sam (==0.1.2)
Requires-Dist: beautifulsoup4 (>=4.13.4,<5.0.0)
Requires-Dist: coco-eval (==0.0.4)
Requires-Dist: datasets (==3.4.0)
Requires-Dist: dotenv (>=0.9.9,<0.10.0)
Requires-Dist: huggingface-hub (>=0.30.2,<0.31.0)
Requires-Dist: mediapipe (==0.10.21)
Requires-Dist: pandas (>=2.2.3,<3.0.0)
Requires-Dist: polars (>=1.27.1,<2.0.0)
Requires-Dist: pytorch-lightning (==2.5.0)
Requires-Dist: requests (>=2.32.4,<3.0.0)
Requires-Dist: rfdetr (>=1.1.0,<1.2.0)
Requires-Dist: supervision (==0.26.0rc7)
Requires-Dist: torch (>=2.6.1)
Requires-Dist: ultralytics (>=8.3.116,<9.0.0)
Project-URL: Bug Tracker, https://github.com/dylandru/BaseballCV/issues
Project-URL: Documentation, https://baseballcv.com
Project-URL: Homepage, https://github.com/dylandru/BaseballCV
